kiez/__init__.py
kiez/analysis/__init__.py
kiez/analysis/estimation.py
kiez/evaluate/__init__.py
kiez/evaluate/eval_metrics.py
kiez/hubness_reduction/__init__.py
kiez/hubness_reduction/base.py
kiez/hubness_reduction/csls.py
kiez/hubness_reduction/dis_sim.py
kiez/hubness_reduction/local_scaling.py
kiez/hubness_reduction/mutual_proximity.py
kiez/io/data_loading.py
kiez/io/temp_file_handling.py
kiez/kiez.py
kiez/neighbors/__init__.py
kiez/neighbors/approximate/__init__.py
kiez/neighbors/approximate/faiss.py
kiez/neighbors/approximate/nmslib.py
kiez/neighbors/approximate/nng.py
kiez/neighbors/approximate/random_projection_trees.py
kiez/neighbors/exact/__init__.py
kiez/neighbors/exact/sklearn_nearest_neighbors.py
kiez/neighbors/neighbor_algorithm_base.py
kiez/neighbors/util.py
kiez/py.typed
kiez-0.5.0.dist-info/LICENSE
kiez-0.5.0.dist-info/WHEEL
kiez-0.5.0.dist-info/METADATA
kiez-0.5.0.dist-info/RECORD
