Metadata-Version: 2.1
Name: kiez
Version: 0.5.0
Summary: Hubness reduced nearest neighbor search for entity alignment with knowledge graph embeddings
Home-page: https://github.com/dobraczka/kiez
License: BSD
Keywords: embedding,hubness,knowledge graph,entity resolution,approximate nearest neighbor search,nearest neighbors,knowledge graph embedding
Author: Daniel Obraczka
Author-email: obraczka@informatik.uni-leipzig.de
Requires-Python: >=3.8,<4.0
Classifier: Development Status :: 4 - Beta
Classifier: Intended Audience :: Developers
Classifier: Intended Audience :: Science/Research
Classifier: License :: OSI Approved :: BSD License
Classifier: License :: Other/Proprietary License
Classifier: Programming Language :: Python :: 3
Classifier: Programming Language :: Python :: 3.8
Classifier: Programming Language :: Python :: 3.9
Classifier: Programming Language :: Python :: 3.10
Classifier: Programming Language :: Python :: 3.11
Classifier: Topic :: Scientific/Engineering
Classifier: Topic :: Software Development :: Libraries
Provides-Extra: annoy
Provides-Extra: docs
Provides-Extra: ngt
Provides-Extra: nmslib
Requires-Dist: Sphinx (>=5.0.0,<6.0.0) ; extra == "docs"
Requires-Dist: annoy (>=1.17.0,<2.0.0) ; extra == "annoy"
Requires-Dist: class-resolver (>=0.3)
Requires-Dist: insegel (>=1.3.1,<2.0.0) ; extra == "docs"
Requires-Dist: joblib (>=1.2.0,<2.0.0)
Requires-Dist: ngt (>=1.8,<2.0) ; extra == "ngt"
Requires-Dist: nmslib (>=2.1.1,<3.0.0) ; extra == "nmslib"
Requires-Dist: numpy (>=1.21.0,<2.0.0)
Requires-Dist: pandas (>=1.1.5,<2.0.0)
Requires-Dist: scikit-learn (>=0.24.1,<2.0.0)
Requires-Dist: scipy (>=1.3.2,<2.0.0)
Requires-Dist: tqdm (>=4.62.3,<5.0.0)
Project-URL: Documentation, https://kiez.readthedocs.io/
Project-URL: Repository, https://github.com/dobraczka/kiez
